django_ner_trainer-0.1.0.dist-info/METADATA
django_ner_trainer-0.1.0.dist-info/RECORD
django_ner_trainer-0.1.0.dist-info/WHEEL
django_ner_trainer-0.1.0.dist-info/top_level.txt
ner_trainer/__init__.py
ner_trainer/apps.py
ner_trainer/conf.py
ner_trainer/forms.py
ner_trainer/models.py
ner_trainer/serializers.py
ner_trainer/spacy_utils.py
ner_trainer/urls.py
ner_trainer/validators.py
ner_trainer/views.py
ner_trainer/management/__init__.py
ner_trainer/management/commands/__init__.py
ner_trainer/management/commands/download_spacy_model.py
ner_trainer/management/commands/package_ner_model.py
ner_trainer/management/commands/train_ner_model.py
ner_trainer/migrations/0001_initial.py
ner_trainer/migrations/__init__.py
ner_trainer/static/css/ner_trainer.css
ner_trainer/static/js/ner_trainer.js
ner_trainer/templates/ner_trainer/base.html
