Metadata-Version: 2.1
Name: django-ner-trainer
Version: 0.1.0
Summary: Tools for training spaCy Named Entity Recognition models in Django
Home-page: https://github.com/johnfraney/django-ner-trainer
Author: John Franey
Author-email: johnfraney@gmail.com
License: MIT
Keywords: django-ner-trainer
Platform: UNKNOWN
Classifier: Development Status :: 3 - Alpha
Classifier: Framework :: Django :: 1.11
Classifier: Framework :: Django :: 2.0
Classifier: Intended Audience :: Developers
Classifier: License :: OSI Approved :: BSD License
Classifier: Natural Language :: English
Classifier: Programming Language :: Python :: 2
Classifier: Programming Language :: Python :: 2.7
Classifier: Programming Language :: Python :: 3
Classifier: Programming Language :: Python :: 3.4
Classifier: Programming Language :: Python :: 3.5
Classifier: Programming Language :: Python :: 3.6
